[
  {
    "id": "ice-kachang-2024 1",
    "title": "Ice Kachang 2024",
    "time": "2024-04-02T18:00:00",
    "location": "401-318 Engineering Atrium (Level 3)",
    "description": "Hot, stressed and over Uni already? Say less... we've got the perfect cooldown for you. Come chill with SSA at our Ice Kachang Night. Sweet, icy, colourful... but there's a twist 👀",
    "memberPrice": "$5",
    "nonMemberPrice": "$11",
    "imageUrl": "",
    "status": "open"
  },
  {
    "id": "ice-kachang-2026 1",
    "title": "Ice Kachang 2026",
    "time": "2026-04-02T18:00:00",
    "location": "401-318 Engineering Atrium (Level 3)",
    "description": "Hot, stressed and over Uni already? Say less... we've got the perfect cooldown for you. Come chill with SSA at our Ice Kachang Night. Sweet, icy, colourful... but there's a twist 👀",
    "memberPrice": "$5",
    "nonMemberPrice": "$11",
    "imageUrl": "",
    "status": "open"
  },

  {
    "id": "ice-kachang-2025 2",
    "title": "Ice Kachang 2025",
    "time": "2025-04-02T18:00:00",
    "location": "401-318 Engineering Atrium (Level 3)",
    "description": "Hot, stressed and over Uni already? Say less... we've got the perfect cooldown for you. Come chill with SSA at our Ice Kachang Night. Sweet, icy, colourful... but there's a twist 👀",
    "memberPrice": "$5",
    "nonMemberPrice": "$11",
    "imageUrl": "",
    "status": "open"
  },
  {
    "id": "ice-kachang-2025 2",
    "title": "Ice Kachang",
    "time": "2025-04-02T18:00:00",
    "location": "401-318 Engineering Atrium (Level 3)",
    "description": "Hot, stressed and over Uni already? Say less... we've got the perfect cooldown for you. Come chill with SSA at our Ice Kachang Night. Sweet, icy, colourful... but there's a twist 👀",
    "memberPrice": "$5",
    "nonMemberPrice": "$11",
    "imageUrl": "",
    "status": "open"
  }
]
